README.md
setup.py
lbk/__init__.py
lbk/api.py
lbk/client.py
lbk/config.py
lbk_cli.egg-info/PKG-INFO
lbk_cli.egg-info/SOURCES.txt
lbk_cli.egg-info/dependency_links.txt
lbk_cli.egg-info/entry_points.txt
lbk_cli.egg-info/requires.txt
lbk_cli.egg-info/top_level.txt